Metadata-Version: 2.1
Name: oneNeuron-pypi-Gopichandyarra
Version: 0.0.2
Summary: Its an implimentation of Perceptron
Home-page: https://github.com/Gopichandyarra/oneNeuron_pypi
Author: Gopichandyarra
Author-email: Gopichandyarra.1@gmail.com
License: UNKNOWN
Project-URL: Bug Tracker, https://github.com/Gopichandyarra/oneNeuron_pypi/issues
Platform: UNKNOWN
Classifier: Programming Language :: Python :: 3
Classifier: License :: OSI Approved :: MIT License
Classifier: Operating System :: OS Independent
Requires-Python: >=3.7
License-File: LICENSE
Requires-Dist: numpy
Requires-Dist: pandas
Requires-Dist: tqdm
